foundationx/__init__.py
foundationx/bootstrap/__init__.py
foundationx/bootstrap/cli.py
foundationx-0.1.0.dist-info/licenses/LICENSE
foundationx-0.1.0.dist-info/METADATA
foundationx-0.1.0.dist-info/WHEEL
foundationx-0.1.0.dist-info/entry_points.txt
foundationx-0.1.0.dist-info/top_level.txt
foundationx-0.1.0.dist-info/RECORD
