Metadata-Version: 2.4
Name: foundationx
Version: 0.1.0
Summary: FoundationX Bootstrap
License: MIT
Requires-Python: >=3.11
License-File: LICENSE
Requires-Dist: click>=8.0.0
Dynamic: license-file
